<?xml version="1.0"?>
  <database name="MODIFIED TABLE C_INVOICE">
    <table name="C_INVOICE" primaryKey="C_INVOICE_KEY">
      <column name="EM_B2BERS_VALIDATIONSTATUS" primaryKey="false" required="true" type="VARCHAR" size="60" autoIncrement="false">
        <default><![CDATA[N/A]]></default>
        <onCreateDefault/>
      </column>
      <column name="EM_B2BERS_VALIDATEBUTTON" primaryKey="false" required="true" type="CHAR" size="1" autoIncrement="false">
        <default><![CDATA[N]]></default>
        <onCreateDefault/>
      </column>
      <column name="EM_B2BERS_PENDINGVALIDDATE" primaryKey="false" required="false" type="TIMESTAMP" size="7" autoIncrement="false">
        <default/>
        <onCreateDefault/>
      </column>
    </table>
  </database>
